{"33CPJdJGsAaB6hmYI1cLvA==":"whatsapp%20image%202018-02-26%20at%2014.49.41-122x122.jpg","AZ/m//75FIGtq42OtVjRWg==":"smart-110x110.png","0fc3665J01ZuFdIEt78Dug==":"240-186x186.png","4cWOmgszjsqucLSUNAqY8Q==":"1920-1920x1080.jpg","pC1wSlRuEK4EWpxK2DBIrA==":"1920-1-1920x1080.jpg","FKK0HEbZGGsejMtpgMWBzQ==":"e7ab16ec-ff1c-446f-9a17-14e7e81ebcb6-1280x719.jpg","OF3q3+pPERCMuO7+7Hc4zw==":"240-1-186x186.png","lA9Fj/sbW3XsikD5rAmRGA==":"240-dark-240x240.png","Uef1Vp4elLvYrsOX186WFw==":"240-dark-1-240x240.png","bWCaZ0d1i34pm+EvxQrZBw==":"e7ab16ec-ff1c-446f-9a17-14e7e81ebcb6-1-1280x719.jpg","a108qzFAAiwDFPXXgIK3CQ==":"19202-1920x1080.jpg","O6Qc5d3pRwfW2w1zJXEDJg==":"19202-1-1920x1080.jpg","SJbd+PBmpbcwlqus9iqdTg==":"11-1897x1067.jpg","MfBdkx7G53hDlJiZ5Vjh5g==":"4-1897x1067.jpg","AN+btN5yKNB34DoUVs8L6A==":"10-1897x1067.jpg","dvByAGLZtMUOKORkZLKYdw==":"3-1897x1067.jpg","e4udLeh6YKMgM4szdK4ToA==":"6-1897x1067.jpg","1xZk6Y2QBDGabeNZI7C0Wg==":"8-1897x1067.jpg","u2QzPnNjxHaKqKiwbyyZtg==":"ss%20final%20logo%202-252x202.png","hnqdEhxSyZbg6OlMVy3bMw==":"smart-1181x1181.png","CvLw6Rx2QnLR0boTY21VIA==":"smart-1-1181x1181.png","gijqNSrQsPA3OW7W/Y0AoA==":"smart-2-1181x1181.png","gbH33jbsHZaWy6UnR4qBoQ==":"untitled-300x168.png","yVO6ExeL8zdxWWUK4Nx6ig==":"images-284x177.jpg","SKbsCu5jbRbBsA0svt24kg==":"2-1897x1067.jpg","vK0pcg8G7Z46wCEifbXQEA==":"ss-192x170.png","HnFTsgtJCa0QlD5w8XuHjw==":"%D8%AE%D9%84%D9%81%D9%8A%D8%A9-1600x899.png","RrJsPFz7C8DI+lWNU8siFw==":"imagesbjbiinu6-214x236.jpg","AHEXPtGAb4QqP1zf7rP8JQ==":"e7ab16ec-ff1c-446f-9a17-14e7e81ebcb6-2-1280x719.jpg","Su2AS4k9U/KMDJWU+WQ9+Q==":"1-1897x1067.jpg","fjQSK6S3xpO/1Y01G3TQKA==":"9-1897x1067.jpg","vZBlXxSItaaMbM3F+h7piw==":"28--280x60.png","Bn6rJsmCUKwWuDOCEdPPIw==":"whatsapp%20image%202018-02-25%20at%2018.39.56%20(1)-630x1102.jpg","sssS4BHGvADg7LF/XZJ0sQ==":"whatsapp%20image%202018-02-25%20at%2018.39.56%20(1)-630x1102.jpg","UuIp3SVOStWGWsaUpn/NrQ==":"whatsapp%20image%202018-02-26%20at%2014.49.41%20(1)-1181x1181.jpg","ygcamF693+K3zfkq6x51rg==":"2-1-1897x1067.jpg","Fbg1qPAYldx0v62CEchPkg==":"2-2-1897x1067.jpg","x7rmjWZ6J9mh3emHzbusag==":"2-3-1897x1067.jpg","01JdEqjiqaTR6jLLQcfm3w==":"2-4-1897x1067.jpg","FWTkbhanx6/z7HZjn1HvgA==":"mbr-1920x1280.jpg","oDBS1suFOag6HBf2+u+dzA==":"mbr-1920x1276.jpg","FSH4o/xjh9u9EVU6cIn0eA==":"mbr-1920x960.jpg","jvZVw+rD11ItDbVwJX08ig==":"3-1-1897x1067.jpg","qQOOFg/G1wyZxhxH65vhGw==":"whatsapp%20image%202018-02-25%20at%2018.39.54-630x1102.jpg","8O7cBWGNSSPxOzHej/SLMg==":"whatsapp%20image%202018-02-26%20at%2014.49.41-1181x1181.jpg","WSUCB0Qb2td0MkdK7vrjfA==":"whatsapp%20image%202018-02-26%20at%2014.49.41-1181x1181.jpg","fuCMKhH5Dn/eBQBsSAeZGw==":"img-20171229-wa0058-678x678.jpg","2GKAUGVd90XyUQEQCln9Sg==":"img-20171229-wa0031-1144x1144.jpg","jHa7f6mxodUkWf2YBKljJw==":"img-20171229-wa0060-678x678.jpg","BEZlP/bP/BiqXA1IRG+xWA==":"whatsapp%20image%202018-02-26%20at%2014.49.41%20(1)-1181x1181.jpg","/gshGKKOe57KuGfxCa62rA==":"img-20171229-wa0061-630x1102.jpg","OEs9Ta8d14F+HMRCVEHdOA==":"img-20171229-wa0061-1-630x1102.jpg","KSiMDixQQXEJHZ5xMd6VKg==":"img-20171229-wa0206-678x678.jpg","I7Q8ZR1tWe7XUGoUkkAxAg==":"logo%20e-a-1144x516.jpg","VgjOPXFJSMOT3FS961Vf5A==":"bc.back-252x144.jpg","nyPVM3g7pYIDK1sfngG82g==":"logo-678x565.jpg","PgHkIiGB06/E2DrthbRBYw==":"ses-894x715.png","aElH/DxicsR4LuF0jgrHvw==":"wateeny%20logo-malek-626x174.png"}